{
  "generatedAt": "2026-04-16T17:45:00",
  "date": "16/04/2026",
  "count": 11,
  "ppts": [
    {
      "fichier": "Eclaireur_Anne-Lise_16_04_2026.pptx",
      "societe": "ECLAIREUR",
      "type": "eclaireur",
      "titre": "ÉCLAIREUR",
      "sousTitre": "Economie et Marchés Financiers — 16/04/2026",
      "auteur": "Anne-Lise Cornen",
      "recommandation": "",
      "cartes": [
        {
          "sujet": "CONFLIT AU MOYEN-ORIENT",
          "contenu": "La poursuite du dialogue entretient l'espoir de paix\nBrent : 94.8 USD/Barrel\nStrait of Hormuz : 53 278 bateaux\nSources : Macrobond, CIC CIB"
        },
        {
          "sujet": "BANQUES CENTRALES",
          "contenu": "Moins de nécessité à relever les taux directeurs\nFed : -9 bp / -0.4 hausse\nBCE : +58 bp / 2.3 hausses\nBoE : +36 bp / 1.5 hausses\nSources : Macrobond, CIC CIB"
        },
        {
          "sujet": "TAUX SOUVERAINS",
          "contenu": "Potentiel de rechute sur la partie courte en Europe\n2 ans : UK 4.2% | US 3.7% | FR 2.7% | DE 2.5%\n10 ans : UK 4.8% | US 4.3% | FR 3.7% | DE 3.0%\nSources : Macrobond, CIC CIB"
        },
        {
          "sujet": "CHINE : CROISSANCE",
          "contenu": "L'économie tient grâce aux exportations\nPIB : 5%\nProduction industrielle : 5.7%\nVentes au détail : 1.7%\nSources : Macrobond, CIC CIB"
        }
      ],
      "parsedAt": "2026-04-16T17:45:00"
    },
    {
      "fichier": "Euronext160426.pptx",
      "societe": "EURONEXT",
      "titre": "EURONEXT",
      "sousTitre": "RECHERCHE ACTIONS",
      "recommandation": "",
      "cartes": [
        {
          "sujet": "Le CIC est teneur de marché obligataire sur Euronext N.V.",
          "contenu": "Un acteur majeur en Europe"
        }
      ],
      "parsedAt": "2026-04-16T09:43:03",
      "type": "actions"
    },
    {
      "fichier": "Forvia Morning 13 04 2026.pptx",
      "societe": "FORVIA",
      "titre": "FORVIA",
      "sousTitre": "RECHERCHE ACTIONS",
      "recommandation": "",
      "cartes": [
        {
          "sujet": "Retour roadshow: focus stratégique /technos & métiers gagnants",
          "contenu": "Growth: Electronics, Seating\nValue: Clean Mob, Lifecycle Solutions, Clarion, Lighting"
        },
        {
          "sujet": "Stratégie",
          "contenu": "Négociations en phase finale, non impactées par le contexte géopolitique"
        },
        {
          "sujet": "Cession d’Interiors",
          "contenu": "Croissance organique 2028 revenus +2% cagr\nGains de marge liés aux mesures restructurations"
        },
        {
          "sujet": "Perspectives",
          "contenu": "Exposition directe extrêmement limitée\nEnergie 1% CA, transport 1% CA, mat.1ères indexées"
        }
      ],
      "parsedAt": "2026-04-16T09:43:03",
      "type": "actions"
    },
    {
      "fichier": "GLevents_Emmanuel Chevalier Presentation 16-04-2026.pptx",
      "societe": "GL EVENTS",
      "titre": "GL EVENTS",
      "sousTitre": "RECHERCHE ACTIONS",
      "recommandation": "",
      "cartes": [
        {
          "sujet": "CA T1-26 : un très bon départ !",
          "contenu": "Très bon CA T1-26 à 468,1 M€ (+9,4% à pcc), supérieur à notre attenteLes grands évènements compensent l’effet de biennalisé défavorable"
        },
        {
          "sujet": "Le CIC a signé un contrat de liquidité avec GL Events.",
          "contenu": "Objectifs 2026 réitérés : CA en croissance à pcc de plus de 8%, ROC en croissance. DFN à nouveau en baisse avec des CAPEX d’~80 M€"
        }
      ],
      "parsedAt": "2026-04-16T09:43:03",
      "type": "actions"
    },
    {
      "fichier": "Havas_Emmanuel Chevalier Presentation 15-04-2026.pptx",
      "societe": "HAVAS NV",
      "titre": "HAVAS NV",
      "sousTitre": "RECHERCHE ACTIONS",
      "recommandation": "",
      "cartes": [
        {
          "sujet": "T1-2026 en ligne. Objectifs 2026 réitérés",
          "contenu": "Croissance org. à +2,5%. Différence par zone. : Les US plus dynamique que prévu  les autres zones moins"
        },
        {
          "sujet": "Revenu T1-26 en ligne",
          "contenu": "1,9% du CA principalement dans la zone Asie-Pacifique et Afrique. -10% sur le mois de mars."
        },
        {
          "sujet": "Pas d’impact de la guerre en Iran",
          "contenu": "croissance org. entre 2 et 3% (vs +2,5% est.), marge op. entre 13,2 et 13,5% (vs 13,3% est.) et pay-out de 40%"
        },
        {
          "sujet": "Perspectives : Objectifs réitérés",
          "contenu": "Dividende, rachat d’action et acquisitions ciblées. Ne s’interdit pas une opération plus structurante !"
        }
      ],
      "parsedAt": "2026-04-16T09:43:03",
      "type": "actions"
    },
    {
      "fichier": "KB.pptx",
      "societe": "KAUFMAN & BROAD",
      "titre": "KAUFMAN & BROAD",
      "sousTitre": "RECHERCHE ACTIONS",
      "recommandation": "",
      "cartes": [
        {
          "sujet": "CA T1 en recul, marges en progression et guidance confirmée",
          "contenu": "Un CA T1 en recul de 5,7% mais pas le plus significatif\n env. 20% du CA annuel et année d’élection municipale"
        },
        {
          "sujet": "Le CIC a signé un contrat de recherche sponsorisée avec Kaufman & Broad conformé",
          "contenu": "Solidité bilancielle. Trésorerie nette positive de plus de 300 M€"
        }
      ],
      "parsedAt": "2026-04-16T09:43:03",
      "type": "actions"
    },
    {
      "fichier": "Kering - PPT CA T1 2026.pptx",
      "societe": "KERING",
      "titre": "KERING",
      "sousTitre": "RECHERCHE ACTIONS",
      "recommandation": "",
      "cartes": [
        {
          "sujet": "Objectifs 2026 confirmés malgré un Gucci toujours à la peine",
          "contenu": "3,6 MM€, +0% en comparable\n=> en ligne avec les attentes"
        },
        {
          "sujet": "CA T1 2026",
          "contenu": "Mode & Maroquinerie : -3% dont -8% pour Gucci\nKering Jewelry : +22%"
        },
        {
          "sujet": "Faits marquants du trimestre",
          "contenu": "Objectifs 2026 confirmés : renouer avec la croissance et améliorer les marges (y compris pour Gucci)"
        },
        {
          "sujet": "Perspectives",
          "contenu": "Recommandation Achat confirmée"
        }
      ],
      "parsedAt": "2026-04-16T09:43:03",
      "type": "actions"
    },
    {
      "fichier": "MM Banques françaises 15.04.26.pptx",
      "societe": "Banques Françaises",
      "titre": "Banques Françaises",
      "sousTitre": "RECHERCHE ACTIONS",
      "recommandation": "",
      "cartes": [
        {
          "sujet": "Previews T1-2026 des banques françaises",
          "contenu": "- CIB : impact négatif du FX et de la géopo ; impact >0 de la volatilité- Retail : hausse marge d’intérêt (mix dépôts favorable)\n- AM : Hausse des AuM et effet de marché >0 ; FX <0 ; Conso. Axa IM"
        },
        {
          "sujet": "Revenus",
          "contenu": "- SG : baisse des coûts (-3% en 2026) avec objectif C/I < 60%  - BNPP : 800 M€ coûts de transformation en 2026 (-300 M€ au T1-26)- CASA : déconsolidation Amundi US"
        },
        {
          "sujet": "Coûts d’exploitation",
          "contenu": "- Conformes aux guidances (BNPP <40 pb ; SG 25-30 pb ; CASA ~40 pb) \n- CASA : signes de détérioration sur PME et professionnels\n- Commentaires complémentaires sur Iran et private debt ?"
        },
        {
          "sujet": "Coût du risque",
          "contenu": "- SG : plus-values cessions de 202 M€ au T1-25 ; CET1 : -6 bp (Bernstein)- CASA:  surtaxe fiscale de -147 M€ en 2025 (reconduite en 2026)- BNPP: plus-value de 800 M€ sur Ageas au T2-2026"
        }
      ],
      "parsedAt": "2026-04-16T09:43:03",
      "type": "actions"
    },
    {
      "fichier": "Pernod - 16 04 26.pptx",
      "societe": "PERNOD RICARD",
      "titre": "PERNOD RICARD",
      "sousTitre": "RECHERCHE ACTIONS",
      "recommandation": "",
      "cartes": [
        {
          "sujet": "Révision en baisse de la guidance de CA annuel",
          "contenu": "La croissance du CA en organique est de 0,1% au T3, mieux qu’attendu (consensus : -0,7% et CIC : -1,4%)"
        },
        {
          "sujet": "Le CIC est teneur de marché obligataire sur Pernod Ricard S.A.",
          "contenu": "La société indique qu’elle devrait maintenir sa marge opérationnelle courante autant que possible grâce à des économies de 1 MM€"
        }
      ],
      "parsedAt": "2026-04-16T09:43:03",
      "type": "actions"
    },
    {
      "fichier": "Pluxee - C Devismes - Morning - 16 avril 2026.pptx",
      "societe": "PLUXEE",
      "titre": "PLUXEE",
      "sousTitre": "RECHERCHE ACTIONS",
      "recommandation": "",
      "cartes": [
        {
          "sujet": "Faible croissance au T2 2026, confirmation des guidances 2026",
          "contenu": "La croissance organique du chiffre d’affaires opérationnel ralenti fortement au T2 2026 : +2,8% vs +9,1% au T1 2026"
        },
        {
          "sujet": "Le CIC est teneur de marché obligataire sur Pluxee.",
          "contenu": "Nous maintenons notre opinion Neutre sur le titre.\nRéunion d’informations à 8h30 (CET)"
        }
      ],
      "parsedAt": "2026-04-16T09:43:03",
      "type": "actions"
    },
    {
      "fichier": "Veolia-MM-150426.pptx",
      "societe": "VEOLIA",
      "titre": "VEOLIA",
      "sousTitre": "RECHERCHE ACTIONS",
      "recommandation": "",
      "cartes": [
        {
          "sujet": "L’IA et le digital au service de la croissance et de la rentabilité",
          "contenu": "Au service de la sécurité écologique\n1 MM€ d’investissement dans plan GreenUp 2024-27"
        },
        {
          "sujet": "La techno chez Veolia",
          "contenu": "259 M€ de CA en 2025 (+25%), 0,6% total \n1 MM€ en 2030 (TMVA +30%)"
        },
        {
          "sujet": "PFAS (eau + déchets)",
          "contenu": "Chaleur + ressource en eau + recyclage\n560 M€ CA 2025 (1,3% total), 1 MM€ en 2030 (+12%/an)"
        },
        {
          "sujet": "Datacenters + micro électro.",
          "contenu": "Organique 2025 (+2,8% ex. énergie) – 2026 +3,4%\nIA + Digital = 50% efficacité op. (23% de 399 M€ en 25)"
        }
      ],
      "parsedAt": "2026-04-16T09:43:03",
      "type": "actions"
    }
  ]
}
