{"updated":"2026-02-26T09:29:53.0213266+01:00","count":20,"drafts":[{"id":"59c494b7-5d07-4982-acf3-14bfe4cf485d","title":"Chart Equity du 26 février","date":"26/02/2026 08:43:00","tags":"Morning Meeting - Recherche Actions, FR, ENGIE, A la Une principale","url":"https://prsnet-si.cm-cic.fr/GRDC_WEB2_B/WebContentPage.aspx?key=59c494b7-5d07-4982-acf3-14bfe4cf485d","author":"Bellin Eva","state":"Brouillon"},{"id":"7b52135e-9982-4579-8348-288b4f3dd5d7","title":"Arverne - visite de site","date":"26/02/2026 09:23:35","tags":"","url":"https://prsnet-si.cm-cic.fr/GRDC_WEB2_B/WebContentPage.aspx?key=7b52135e-9982-4579-8348-288b4f3dd5d7","author":"","state":""},{"id":"57bd8494-8709-4c5b-81ef-166162c38adc","title":"[HOT] Engie :","date":"26/02/2026 09:23:00","tags":"Direct analystes - Recherche Actions, FR, A la Une secondaire, ENGIE","url":"https://prsnet-si.cm-cic.fr/GRDC_WEB2_B/WebContentPage.aspx?key=57bd8494-8709-4c5b-81ef-166162c38adc","author":"Palliez Arnaud","state":"Brouillon"},{"id":"950b3a22-9c7e-406c-9661-7dbec981d846","title":"Saipem - Sound 2025 results and promising outlook (21 pages)","date":"26/02/2026 09:17:07","tags":"","url":"https://prsnet-si.cm-cic.fr/GRDC_WEB2_B/WebContentPage.aspx?key=950b3a22-9c7e-406c-9661-7dbec981d846","author":"Sala Francesco","state":""},{"id":"4fd74d12-194c-487e-8c25-d74bf4cb14dc","title":"UmweltBank - Buy - EBT guidance in line - Positive outlook for 2026 - Comment (1 page)","date":"26/02/2026 09:14:12","tags":"","url":"https://prsnet-si.cm-cic.fr/GRDC_WEB2_B/WebContentPage.aspx?key=4fd74d12-194c-487e-8c25-d74bf4cb14dc","author":"","state":""},{"id":"ae4253c5-6bb4-4e05-9d89-262888d342e0","title":"Datrix - Disseminating AI through a software ecosystem (66 pages)","date":"26/02/2026 09:13:57","tags":"","url":"https://prsnet-si.cm-cic.fr/GRDC_WEB2_B/WebContentPage.aspx?key=ae4253c5-6bb4-4e05-9d89-262888d342e0","author":"Zappa Davide","state":""},{"id":"ddeddc9b-1823-47f5-bbae-38b974f39130","title":"Smartbroker - Buy - Preliminary 2025 figures in line - Further improvement expected in 2026 - Comment (1 page)","date":"26/02/2026 09:13:16","tags":"","url":"https://prsnet-si.cm-cic.fr/GRDC_WEB2_B/WebContentPage.aspx?key=ddeddc9b-1823-47f5-bbae-38b974f39130","author":"","state":""},{"id":"2f4db3b5-5aee-438a-a49c-d4bf22dab181","title":"innoscripta - Buy - FY26 guidance confirms our positive stance - Comment (1 page)","date":"26/02/2026 09:12:11","tags":"","url":"https://prsnet-si.cm-cic.fr/GRDC_WEB2_B/WebContentPage.aspx?key=2f4db3b5-5aee-438a-a49c-d4bf22dab181","author":"","state":""},{"id":"2a81e22e-a17f-46cf-a699-c574619bdd2c","title":"Hoenle AG - Buy - Weak start to the year - Comment (1 page)","date":"26/02/2026 09:11:10","tags":"","url":"https://prsnet-si.cm-cic.fr/GRDC_WEB2_B/WebContentPage.aspx?key=2a81e22e-a17f-46cf-a699-c574619bdd2c","author":"","state":""},{"id":"5638e79c-f4ba-4d4b-9ce9-57850d167002","title":"HENSOLDT - Buy - Year-end business below expectations but fundamental picture intact - Comment (1 page)","date":"26/02/2026 09:10:06","tags":"","url":"https://prsnet-si.cm-cic.fr/GRDC_WEB2_B/WebContentPage.aspx?key=5638e79c-f4ba-4d4b-9ce9-57850d167002","author":"","state":""},{"id":"0e88f62e-8e8c-419b-a744-cad6d92eb61c","title":"Hamborner REIT - Buy - Solid FY25 preliminary figures supported by one-off effects - Comment (1 page)","date":"26/02/2026 09:08:57","tags":"","url":"https://prsnet-si.cm-cic.fr/GRDC_WEB2_B/WebContentPage.aspx?key=0e88f62e-8e8c-419b-a744-cad6d92eb61c","author":"","state":""},{"id":"0560a700-4085-4e5b-a923-1e27e2190e2f","title":"Einhell Pref. - Buy - Strong EBT margin despite lower Q4 sales - Comment (1 page)","date":"26/02/2026 09:07:55","tags":"","url":"https://prsnet-si.cm-cic.fr/GRDC_WEB2_B/WebContentPage.aspx?key=0560a700-4085-4e5b-a923-1e27e2190e2f","author":"","state":""},{"id":"c1b66e7b-df7b-41e3-be1b-872aa1b1ea01","title":"KION Group - Buy - First Glance: Outlook to disappoint - First Glance (1 page)","date":"26/02/2026 09:06:55","tags":"","url":"https://prsnet-si.cm-cic.fr/GRDC_WEB2_B/WebContentPage.aspx?key=c1b66e7b-df7b-41e3-be1b-872aa1b1ea01","author":"","state":""},{"id":"8f2da7d6-4b54-4607-9820-97efe95c467d","title":"Aixtron - Hold - First Glance: Q4 metrics above expectations - sales to decline in 2026 - First Glance (1 page)","date":"26/02/2026 09:05:35","tags":"","url":"https://prsnet-si.cm-cic.fr/GRDC_WEB2_B/WebContentPage.aspx?key=8f2da7d6-4b54-4607-9820-97efe95c467d","author":"","state":""},{"id":"6437c04d-8154-4fe4-852c-da4b903bb2ba","title":"ADTRAN - Buy - First Glance: Q1 guidance slightly ahead of estimates - First Glance (1 page)","date":"26/02/2026 09:03:47","tags":"","url":"https://prsnet-si.cm-cic.fr/GRDC_WEB2_B/WebContentPage.aspx?key=6437c04d-8154-4fe4-852c-da4b903bb2ba","author":"","state":""},{"id":"38017a31-f719-4792-958d-700f7ac92af6","title":"ARKEMA, BUREAU VERITAS, EIFFAGE, ENGIE, FNAC DARTY, SCHNEIDER ELECTRIC, WORLDLINE, WPP (11 pages)","date":"26/02/2026 08:59:29","tags":"","url":"https://prsnet-si.cm-cic.fr/GRDC_WEB2_B/WebContentPage.aspx?key=38017a31-f719-4792-958d-700f7ac92af6","author":"","state":""},{"id":"ca555e4b-8da5-4a86-9a02-f33f73412cae","title":"CIC CIB Morning Analyser - 26/02/2026 (56 pages)","date":"26/02/2026 08:57:02","tags":"CIC Morning News analyser, 74Software, Arkema, AXA, Bouygues, Edenred, Eiffage, ENGIE, EssilorLuxottica, Fnac Darty, GBL, Getlink, Interparfums, Michelin, Nexity, OPmobility, Rolls-Royce Holdings Plc, Schneider Electric, Sopra Steria Group, Technip Energies, Veolia , Wendel , Worldline, FR","url":"https://prsnet-si.cm-cic.fr/GRDC_WEB2_B/WebContentPage.aspx?key=ca555e4b-8da5-4a86-9a02-f33f73412cae","author":"","state":""},{"id":"34d09c48-c674-4951-9d31-b611824254f2","title":"Schneider Electric : 2025 en ligne, perspective sans surprise","date":"26/02/2026 08:51:00","tags":"Morning Meeting - Recherche Actions, Schneider Electric, FR, A la Une secondaire","url":"https://prsnet-si.cm-cic.fr/GRDC_WEB2_B/WebContentPage.aspx?key=34d09c48-c674-4951-9d31-b611824254f2","author":"","state":""},{"id":"5990e0e9-9d55-46f7-b32f-a6f51a65dace","title":"Des négociations internationales incertaines (6 pages)","date":"26/02/2026 08:46:51","tags":"","url":"https://prsnet-si.cm-cic.fr/GRDC_WEB2_B/WebContentPage.aspx?key=5990e0e9-9d55-46f7-b32f-a6f51a65dace","author":"","state":""},{"id":"1f549282-9eab-4303-ad10-4197718e4f1d","title":"Engie : Objectifs de résultats relevés et acquisition de UK Power Networks","date":"26/02/2026 08:43:00","tags":"Morning Meeting - Recherche Actions, FR, ENGIE, A la Une principale","url":"https://prsnet-si.cm-cic.fr/GRDC_WEB2_B/WebContentPage.aspx?key=1f549282-9eab-4303-ad10-4197718e4f1d","author":"","state":""}]}